liaa/__init__.py
liaa/app.py
liaa/crawling.py
liaa/exception.py
liaa/network.py
liaa/node.py
liaa/protocol.py
liaa/routing.py
liaa/storage.py
liaa/utils.py
tests/__init__.py
tests/conftest.py
tests/test_crawling.py
tests/test_linting.py
tests/test_network.py
tests/test_node.py
tests/test_protocol.py
tests/test_routing.py
tests/test_storage.py
tests/test_utils.py
liaa-1.1.2.dist-info/LICENSE
liaa-1.1.2.dist-info/METADATA
liaa-1.1.2.dist-info/WHEEL
liaa-1.1.2.dist-info/top_level.txt
liaa-1.1.2.dist-info/RECORD
