Metadata-Version: 2.1
Name: liaa
Version: 1.1.2
Summary: Liaa is a distributed hash table for decentralized peer-to-peer computer networks.
Home-page: http://github.com/ralston3/liaa
Author: Brian Muller, Rashad Alston
Author-email: bamuller@gmail.com, rashadalston@gmail.com
License: MIT
Platform: UNKNOWN
Classifier: Development Status :: 5 - Production/Stable
Classifier: Intended Audience :: Developers
Classifier: License :: OSI Approved :: MIT License
Classifier: Operating System :: OS Independent
Classifier: Programming Language :: Python
Classifier: Programming Language :: Python :: 3
Classifier: Programming Language :: Python :: 3.5
Classifier: Programming Language :: Python :: 3.6
Classifier: Programming Language :: Python :: 3.7
Classifier: Topic :: Software Development :: Libraries :: Python Modules
Requires-Dist: u-msgpack-python
